{"stats":{"minecraft:custom":{"minecraft:time_since_rest":19201,"minecraft:crouch_one_cm":3627,"minecraft:sprint_one_cm":32979,"minecraft:play_time":137998,"minecraft:deaths":2,"minecraft:damage_taken":2260,"minecraft:walk_one_cm":74441,"minecraft:sneak_time":2296,"minecraft:mob_kills":1,"minecraft:damage_dealt_resisted":12,"minecraft:jump":517,"minecraft:damage_dealt":423,"minecraft:leave_game":4,"minecraft:time_since_death":19173,"minecraft:total_world_time":137998,"minecraft:climb_one_cm":4861,"minecraft:fall_one_cm":4585,"minecraft:fly_one_cm":129742},"minecraft:killed":{"born_in_chaos_v1:skeleton_thrasher":1},"minecraft:picked_up":{"rpgsmw:class_choose_orb":1},"minecraft:used":{"minecraft:lever":4,"minecraft:sea_lantern":4,"minecraft:snow":4,"minecraft:iron_trapdoor":6,"minecraft:grindstone":1,"minecraft:oak_stairs":4,"minecraft:spruce_slab":1,"minecraft:podzol":31,"minecraft:ladder":15,"minecraft:stone":5,"minecraft:spruce_trapdoor":9,"minecraft:splash_potion":87}},"DataVersion":3465}