{"stats":{"minecraft:killed":{"born_in_chaos_v1:skeleton_thrasher":1},"minecraft:custom":{"minecraft:jump":318,"minecraft:time_since_rest":104739,"minecraft:damage_dealt":423,"minecraft:damage_taken":2260,"minecraft:crouch_one_cm":3144,"minecraft:leave_game":3,"minecraft:play_time":106894,"minecraft:sprint_one_cm":21085,"minecraft:time_since_death":104705,"minecraft:walk_one_cm":38449,"minecraft:deaths":1,"minecraft:sneak_time":1678,"minecraft:total_world_time":106894,"minecraft:mob_kills":1,"minecraft:fall_one_cm":4585,"minecraft:fly_one_cm":99519,"minecraft:damage_dealt_resisted":12},"minecraft:picked_up":{"rpgsmw:class_choose_orb":1},"minecraft:used":{"minecraft:splash_potion":87,"minecraft:podzol":31}},"DataVersion":3465}